README.md
setup.py
src/gcp_hashicorp_packer_reaper/__init__.py
src/gcp_hashicorp_packer_reaper/__main__.py
src/gcp_hashicorp_packer_reaper/click_argument_types.py
src/gcp_hashicorp_packer_reaper/gcp.py
src/gcp_hashicorp_packer_reaper/logger.py
src/gcp_hashicorp_packer_reaper/reaper.py
src/gcp_hashicorp_packer_reaper/server.py
src/gcp_hashicorp_packer_reaper.egg-info/PKG-INFO
src/gcp_hashicorp_packer_reaper.egg-info/SOURCES.txt
src/gcp_hashicorp_packer_reaper.egg-info/dependency_links.txt
src/gcp_hashicorp_packer_reaper.egg-info/entry_points.txt
src/gcp_hashicorp_packer_reaper.egg-info/not-zip-safe
src/gcp_hashicorp_packer_reaper.egg-info/requires.txt
src/gcp_hashicorp_packer_reaper.egg-info/top_level.txt